econometron/__init__.py
econometron/Models/StateSpace.py
econometron/Models/__init__.py
econometron/Models/Neuralnets/__init__.py
econometron/Models/Neuralnets/n_beats.py
econometron/Models/VectorAutoReg/SVAR.py
econometron/Models/VectorAutoReg/VAR.py
econometron/Models/VectorAutoReg/VARIMA.py
econometron/Models/VectorAutoReg/VARMA.py
econometron/Models/VectorAutoReg/__init__.py
econometron/Models/dynamicsge/__init__.py
econometron/filters/__init__.py
econometron/utils/__init__.py
econometron/utils/Sampler/__init__.py
econometron/utils/data_preparation/__init__.py
econometron/utils/data_preparation/process_timeseries.py
econometron/utils/data_preparation/scaler.py
econometron/utils/estimation/Bayesian.py
econometron/utils/estimation/MLE.py
econometron/utils/estimation/Regression.py
econometron/utils/estimation/__init__.py
econometron/utils/estimation/results.py
econometron/utils/optimizers/__init__.py
econometron/utils/projection/Local_proj.py
econometron/utils/projection/__init__.py
econometron/utils/projection/basis.py
econometron/utils/solver/__init__.py
econometron/utils/solver/dsge_solv.py
econometron-0.0.4.dist-info/licenses/LICENSE
econometron-0.0.4.dist-info/METADATA
econometron-0.0.4.dist-info/WHEEL
econometron-0.0.4.dist-info/top_level.txt
econometron-0.0.4.dist-info/RECORD
