Metadata-Version: 2.4
Name: econometron
Version: 0.0.4
Summary: A Python library for econometric modeling and multivariate time series forecasting,providing a precise and extensible framework for statistical analysis and computational simulations.
Home-page: https://econometron.netlify.app
Author: Mohamed Amine Ouerfelli
Author-email: mohamedamine.ouerfelli@outlook.com
License: MIT
Project-URL: Source, https://github.com/AmineOuerfellii/econometron
Project-URL: Documentation, https://econometron.netlify.app
Project-URL: Tracker, https://github.com/AmineOuerfellii/econometron/issues
Classifier: Development Status :: 2 - Pre-Alpha
Classifier: Intended Audience :: Science/Research
Classifier: License :: OSI Approved :: MIT License
Classifier: Programming Language :: Python :: 3
Classifier: Programming Language :: Python :: 3.9
Classifier: Topic :: Scientific/Engineering :: Mathematics
Classifier: Topic :: Scientific/Engineering :: Information Analysis
Classifier: Operating System :: OS Independent
Requires-Python: >=3.8
License-File: LICENSE
Requires-Dist: numpy>=1.23.5
Requires-Dist: pandas>=1.5.3
Requires-Dist: scipy>=1.13.0
Requires-Dist: matplotlib>=3.8.4
Requires-Dist: statsmodels>=0.14.1
Requires-Dist: sympy>=1.13.0
Requires-Dist: torch>=1.13.1
Requires-Dist: scikit-learn>=1.0.2
Requires-Dist: torchinfo>=1.7.2
Dynamic: author
Dynamic: author-email
Dynamic: classifier
Dynamic: description
Dynamic: description-content-type
Dynamic: home-page
Dynamic: license
Dynamic: license-file
Dynamic: project-url
Dynamic: requires-dist
Dynamic: requires-python
Dynamic: summary
